PlexLabExchange-0.9.3.data/scripts/plex
plex/__init__.py
PlexLabExchange-0.9.3.dist-info/METADATA
PlexLabExchange-0.9.3.dist-info/WHEEL
PlexLabExchange-0.9.3.dist-info/top_level.txt
PlexLabExchange-0.9.3.dist-info/RECORD
